{"Oddish": 93, "Weezing": 147, "Primeape": 110, "Magikarp": 73, "Caterpie": 11, "Paras": 97, "Kadabra": 62, "Growlithe": 49, "Eevee": 30, "Hitmonlee": 53, "Poliwrath": 107, "Machamp": 70, "Butterfree": 10, "Raichu": 112, "Omanyte": 94, "Tangela": 132, "Slowpoke": 126, "Mew": 81, "Dragonair": 25, "Rhydon": 116, "Exeggutor": 35, "Parasect": 98, "Tentacool": 134, "Magnemite": 75, "Ditto": 22, "Aerodactyl": 1, "Koffing": 66, "Shellder": 124, "Lapras": 68, "MrMime": 84, "Mankey": 77, "Dratini": 27, "Nidoqueen": 87, "Charmeleon": 15, "Psyduck": 111, "Slowbro": 125, "Snorlax": 127, "Arcanine": 4, "Omastar": 95, "Sandslash": 119, "Articuno": 5, "Blastoise": 8, "Golem": 46, "Farfetchd": 36, "Dodrio": 23, "Pinsir": 104, "Cloyster": 18, "Beedrill": 6, "Tauros": 133, "Fearow": 37, "Bulbasaur": 9, "Jigglypuff": 57, "Abra": 0, "Arbok": 3, "Doduo": 24, "Muk": 85, "Marowak": 78, "Ponyta": 108, "Wigglytuff": 148, "Porygon": 109, "Raticate": 114, "Graveler": 47, "Chansey": 12, "Geodude": 41, "Pidgeotto": 101, "Rattata": 115, "Kabutops": 61, "Squirtle": 129, "Vulpix": 143, "Bellsprout": 7, "Nidoran\u2642": 89, "Nidoran\u2640": 88, "Jolteon": 58, "Venusaur": 139, "Meowth": 79, "Golduck": 45, "Scyther": 120, "Ekans": 31, "Alakazam": 2, "Seel": 123, "Voltorb": 142, "Kangaskhan": 64, "Dragonite": 26, "Gyarados": 50, "Vaporeon": 136, "Metapod": 80, "Diglett": 21, "Hypno": 55, "Lickitung": 69, "Haunter": 51, "Ivysaur": 56, "Vileplume": 141, "Gastly": 39, "Drowzee": 28, "Goldeen": 44, "Pidgey": 102, "Mewtwo": 82, "Machoke": 71, "Poliwhirl": 106, "Poliwag": 105, "Sandshrew": 118, "Venomoth": 137, "Gloom": 42, "Nidorino": 91, "Nidorina": 90, "Pidgeot": 100, "Spearow": 128, "Kingler": 65, "Exeggcute": 34, "Weepinbell": 146, "Golbat": 43, "Gengar": 40, "Rapidash": 113, "Dugtrio": 29, "Krabby": 67, "Seadra": 121, "Persian": 99, "Nidoking": 86, "Zapdos": 149, "Zubat": 150, "Charmander": 14, "Electrode": 33, "Moltres": 83, "Victreebel": 140, "Flareon": 38, "Kabuto": 60, "Electabuzz": 32, "Venonat": 138, "Charizard": 13, "Pikachu": 103, "Machop": 72, "Jynx": 59, "Kakuna": 63, "Horsea": 54, "Seaking": 122, "Dewgong": 20, "Hitmonchan": 52, "Clefable": 16, "Starmie": 130, "Rhyhorn": 117, "Tentacruel": 135, "Wartortle": 144, "Ninetales": 92, "Cubone": 19, "Weedle": 145, "Onix": 96, "Clefairy": 17, "Grimer": 48, "Magneton": 76, "Magmar": 74, "Staryu": 131}